batch_prediction_pipeline/__init__.py
batch_prediction_pipeline/batch.py
batch_prediction_pipeline/data.py
batch_prediction_pipeline/monitoring.py
batch_prediction_pipeline/settings.py
batch_prediction_pipeline/utils.py
batch_prediction_pipeline_amar-0.1.0.dist-info/METADATA
batch_prediction_pipeline_amar-0.1.0.dist-info/WHEEL
batch_prediction_pipeline_amar-0.1.0.dist-info/RECORD
